{
  "display": {
    "icon": {
      "item": "minecraft:lever"
    },
    "title": {
      "translate":"advancements.underfabric.pillar_puzzle"
    },
    "frame": "task",
    "description": {
      "translate": "advancements.underfabric.pillar_puzzle.description"
    },
    "show_toast": "true",
    "announce_to_chat": "false",
    "hidden": "true"
  },
  "parent": "underfabric:ruins/leaf_pile/mouse/napstablook",
  "criteria": {
    "placeholder": {
      "trigger": "minecraft:impossible"
    }
  }
}